client/__init__.py
client/add_contact.py
client/database.py
client/del_contact.py
client/main_window.py
client/main_window_conv.py
client/start_dialog.py
client/transport.py
common/__init__.py
common/decos.py
common/descryptors.py
common/errors.py
common/metaclasses.py
common/utils.py
common/variables.py
logs/__init__.py
logs/config_client_log.py
logs/config_server_log.py
unit_tests/__init__.py
AsyncClient-0.0.1.dist-info/METADATA
AsyncClient-0.0.1.dist-info/WHEEL
AsyncClient-0.0.1.dist-info/top_level.txt
AsyncClient-0.0.1.dist-info/RECORD
