Metadata-Version: 2.1
Name: AsyncClient
Version: 0.0.1
Summary: Chat with encryption
Author: Ekaterina Eranova
Author-email: kteranova@mail.ru
